eltyer/__init__.py
eltyer/exceptions.py
eltyer/configuration/__init__.py
eltyer/configuration/config.py
eltyer/configuration/constants.py
eltyer/models/__init__.py
eltyer/models/model.py
eltyer/models/order.py
eltyer/models/order_side.py
eltyer/models/order_status.py
eltyer/models/order_type.py
eltyer/models/portfolio.py
eltyer/models/position.py
eltyer/utils/__init__.py
eltyer-0.3.3.dist-info/LICENSE
eltyer-0.3.3.dist-info/METADATA
eltyer-0.3.3.dist-info/WHEEL
eltyer-0.3.3.dist-info/top_level.txt
eltyer-0.3.3.dist-info/RECORD
