Metadata-Version: 2.1
Name: eltyer
Version: 0.3.3
Summary: Official python client for ELTYER
Home-page: https://github.com/ELTYER/eltyer-python-client.git
Author: ELTYER
License: Apache License 2.0
Keywords: ELTYER,eltyer,investing-algorithm,INVESTING,BOT,ALGORITHM,FRAMEWORK,investing-bots,trading-bots
Platform: UNKNOWN
Classifier: Intended Audience :: Developers
Classifier: Programming Language :: Python :: 3
Classifier: Programming Language :: Python :: 3.4
Classifier: Programming Language :: Python :: 3.5
Classifier: Programming Language :: Python :: 3.6
Classifier: Topic :: Software Development
Classifier: License :: OSI Approved :: Apache Software License
Classifier: Operating System :: OS Independent
Requires-Python: >=3
License-File: LICENSE
Requires-Dist: requests (==2.26.0)
